{
    "name": "Ekmungai\\IFRS\\Models\\Vat",
    "line": 32,
    "short_desc": "Class Vat",
    "long_desc": "",
    "hint": null,
    "tags": {
        "package": [
            [
                "Ekmungai\\Laravel-IFRS"
            ]
        ],
        "property": [
            [
                [
                    [
                        "\\Ekmungai\\IFRS\\Models\\Entity",
                        false
                    ]
                ],
                "entity",
                ""
            ],
            [
                [
                    [
                        "string",
                        false
                    ]
                ],
                "code",
                ""
            ],
            [
                [
                    [
                        "string",
                        false
                    ]
                ],
                "name",
                ""
            ],
            [
                [
                    [
                        "float",
                        false
                    ]
                ],
                "rate",
                ""
            ],
            [
                [
                    [
                        "\\Ekmungai\\IFRS\\Models\\Carbon",
                        false
                    ]
                ],
                "destroyed_at",
                ""
            ],
            [
                [
                    [
                        "\\Ekmungai\\IFRS\\Models\\Carbon",
                        false
                    ]
                ],
                "deleted_at",
                ""
            ]
        ]
    },
    "namespace": "Ekmungai\\IFRS\\Models",
    "file": "C:\\laravel-ifrs\\config\/..\/src\\Models\\Vat.php",
    "relative_file": null,
    "hash": "383c46e50fccf5252f3f7b51a16d68f8bfd0149a",
    "parent": "Illuminate\\Database\\Eloquent\\Model",
    "modifiers": 0,
    "is_trait": false,
    "is_interface": false,
    "aliases": {
        "Model": "Illuminate\\Database\\Eloquent\\Model",
        "SoftDeletes": "Illuminate\\Database\\Eloquent\\SoftDeletes",
        "Segragatable": "Ekmungai\\IFRS\\Interfaces\\Segragatable",
        "Recyclable": "Ekmungai\\IFRS\\Interfaces\\Recyclable",
        "Recycling": "Ekmungai\\IFRS\\Traits\\Recycling",
        "Segragating": "Ekmungai\\IFRS\\Traits\\Segragating"
    },
    "errors": [],
    "interfaces": {
        "Ekmungai\\IFRS\\Interfaces\\Segragatable": "Ekmungai\\IFRS\\Interfaces\\Segragatable",
        "Ekmungai\\IFRS\\Interfaces\\Recyclable": "Ekmungai\\IFRS\\Interfaces\\Recyclable"
    },
    "traits": {
        "Ekmungai\\IFRS\\Traits\\Segragating": "Ekmungai\\IFRS\\Traits\\Segragating",
        "Illuminate\\Database\\Eloquent\\SoftDeletes": "Illuminate\\Database\\Eloquent\\SoftDeletes",
        "Ekmungai\\IFRS\\Traits\\Recycling": "Ekmungai\\IFRS\\Traits\\Recycling"
    },
    "properties": {
        "entity": {
            "name": "entity",
            "line": 32,
            "short_desc": "",
            "long_desc": null,
            "hint": [
                [
                    "\\Ekmungai\\IFRS\\Models\\Entity",
                    false
                ]
            ],
            "hint_desc": null,
            "tags": [],
            "modifiers": null,
            "default": null,
            "errors": []
        },
        "code": {
            "name": "code",
            "line": 32,
            "short_desc": "",
            "long_desc": null,
            "hint": [
                [
                    "string",
                    false
                ]
            ],
            "hint_desc": null,
            "tags": [],
            "modifiers": null,
            "default": null,
            "errors": []
        },
        "name": {
            "name": "name",
            "line": 32,
            "short_desc": "",
            "long_desc": null,
            "hint": [
                [
                    "string",
                    false
                ]
            ],
            "hint_desc": null,
            "tags": [],
            "modifiers": null,
            "default": null,
            "errors": []
        },
        "rate": {
            "name": "rate",
            "line": 32,
            "short_desc": "",
            "long_desc": null,
            "hint": [
                [
                    "float",
                    false
                ]
            ],
            "hint_desc": null,
            "tags": [],
            "modifiers": null,
            "default": null,
            "errors": []
        },
        "destroyed_at": {
            "name": "destroyed_at",
            "line": 32,
            "short_desc": "",
            "long_desc": null,
            "hint": [
                [
                    "\\Ekmungai\\IFRS\\Models\\Carbon",
                    false
                ]
            ],
            "hint_desc": null,
            "tags": [],
            "modifiers": null,
            "default": null,
            "errors": []
        },
        "deleted_at": {
            "name": "deleted_at",
            "line": 32,
            "short_desc": "",
            "long_desc": null,
            "hint": [
                [
                    "\\Ekmungai\\IFRS\\Models\\Carbon",
                    false
                ]
            ],
            "hint_desc": null,
            "tags": [],
            "modifiers": null,
            "default": null,
            "errors": []
        }
    },
    "methods": {
        "new": {
            "name": "new",
            "line": 47,
            "short_desc": "Construct new Vat",
            "long_desc": "",
            "hint": [
                [
                    "\\Ekmungai\\IFRS\\Models\\Vat",
                    false
                ]
            ],
            "hint_desc": "",
            "tags": [],
            "modifiers": 9,
            "is_by_ref": "",
            "exceptions": [],
            "errors": [],
            "parameters": {
                "name": {
                    "name": "name",
                    "line": 47,
                    "short_desc": "",
                    "long_desc": null,
                    "hint": [
                        [
                            "string",
                            false
                        ]
                    ],
                    "tags": [],
                    "modifiers": "string",
                    "default": null,
                    "variadic": false,
                    "is_by_ref": false
                },
                "code": {
                    "name": "code",
                    "line": 47,
                    "short_desc": "",
                    "long_desc": null,
                    "hint": [
                        [
                            "string",
                            false
                        ]
                    ],
                    "tags": [],
                    "modifiers": "string",
                    "default": null,
                    "variadic": false,
                    "is_by_ref": false
                },
                "rate": {
                    "name": "rate",
                    "line": 47,
                    "short_desc": "",
                    "long_desc": null,
                    "hint": [
                        [
                            "float",
                            false
                        ]
                    ],
                    "tags": [],
                    "modifiers": "float",
                    "default": null,
                    "variadic": false,
                    "is_by_ref": false
                }
            }
        },
        "attributes": {
            "name": "attributes",
            "line": 63,
            "short_desc": "Vat attributes.",
            "long_desc": "",
            "hint": [
                [
                    "object",
                    false
                ]
            ],
            "hint_desc": "",
            "tags": [],
            "modifiers": 1,
            "is_by_ref": "",
            "exceptions": [],
            "errors": [],
            "parameters": []
        }
    },
    "constants": []
}